[
  {
    "step": {
      "step_id": "get_company_profile_valid",
      "tool_name": "get_company_profile",
      "parameters": {
        "stock_code": "NVDA"
      },
      "description": "Happy path: Retrieve company profile for NVIDIA using a valid stock code."
    },
    "substituted_params": {
      "stock_code": "NVDA"
    },
    "result": {
      "status": "error",
      "result": "Error executing tool get_company_profile: HTTP error occurred: 404 - \n<!doctype html>\n<html lang=\"en\">\n<head>\n  <title>Not Found</title>\n</head>\n<body>\n  <h1>Not Found</h1><p>The requested resource was not found on this server.</p>\n</body>\n</html>\n"
    }
  },
  {
    "step": {
      "step_id": "get_income_statements_valid",
      "tool_name": "get_income_statements",
      "parameters": {
        "stock_code": "$outputs.get_company_profile_valid.ticker",
        "report_period": "annual",
        "limit": 5
      },
      "description": "Dependent call: Fetch annual income statements for NVIDIA with limit=5."
    },
    "substituted_params": {
      "stock_code": null,
      "report_period": "annual",
      "limit": 5
    },
    "result": {
      "status": "error",
      "result": "A required parameter resolved to None, likely due to a failure in a dependency. Failed placeholder: '$outputs.get_company_profile_valid.ticker'"
    }
  },
  {
    "step": {
      "step_id": "get_balance_sheets_valid",
      "tool_name": "get_balance_sheets",
      "parameters": {
        "stock_code": "$outputs.get_company_profile_valid.ticker",
        "report_period": "quarterly",
        "limit": 4
      },
      "description": "Dependent call: Fetch quarterly balance sheets for NVIDIA with limit=4."
    },
    "substituted_params": {
      "stock_code": null,
      "report_period": "quarterly",
      "limit": 4
    },
    "result": {
      "status": "error",
      "result": "A required parameter resolved to None, likely due to a failure in a dependency. Failed placeholder: '$outputs.get_company_profile_valid.ticker'"
    }
  },
  {
    "step": {
      "step_id": "get_cash_flows_valid",
      "tool_name": "get_cash_flows",
      "parameters": {
        "stock_code": "$outputs.get_company_profile_valid.ticker",
        "report_period": "ttm",
        "limit": 10
      },
      "description": "Dependent call: Fetch trailing twelve months (TTM) cash flow data for NVIDIA with limit=10."
    },
    "substituted_params": {
      "stock_code": null,
      "report_period": "ttm",
      "limit": 10
    },
    "result": {
      "status": "error",
      "result": "A required parameter resolved to None, likely due to a failure in a dependency. Failed placeholder: '$outputs.get_company_profile_valid.ticker'"
    }
  },
  {
    "step": {
      "step_id": "get_earnings_history_valid",
      "tool_name": "get_earnings_history",
      "parameters": {
        "stock_code": "$outputs.get_company_profile_valid.ticker"
      },
      "description": "Dependent call: Fetch historical earnings data for NVIDIA."
    },
    "substituted_params": {
      "stock_code": null
    },
    "result": {
      "status": "error",
      "result": "A required parameter resolved to None, likely due to a failure in a dependency. Failed placeholder: '$outputs.get_company_profile_valid.ticker'"
    }
  },
  {
    "step": {
      "step_id": "get_financial_ratios_valid",
      "tool_name": "get_financial_ratios",
      "parameters": {
        "stock_code": "$outputs.get_company_profile_valid.ticker"
      },
      "description": "Dependent call: Retrieve financial ratios like P/E and debt-to-equity for NVIDIA."
    },
    "substituted_params": {
      "stock_code": null
    },
    "result": {
      "status": "error",
      "result": "A required parameter resolved to None, likely due to a failure in a dependency. Failed placeholder: '$outputs.get_company_profile_valid.ticker'"
    }
  },
  {
    "step": {
      "step_id": "get_analyst_estimates_valid",
      "tool_name": "get_analyst_estimates",
      "parameters": {
        "stock_code": "$outputs.get_company_profile_valid.ticker"
      },
      "description": "Dependent call: Get analyst estimates including target prices and forecasts for NVIDIA."
    },
    "substituted_params": {
      "stock_code": null
    },
    "result": {
      "status": "error",
      "result": "A required parameter resolved to None, likely due to a failure in a dependency. Failed placeholder: '$outputs.get_company_profile_valid.ticker'"
    }
  },
  {
    "step": {
      "step_id": "get_dividend_history_valid",
      "tool_name": "get_dividend_history",
      "parameters": {
        "stock_code": "$outputs.get_company_profile_valid.ticker"
      },
      "description": "Dependent call: Retrieve dividend history for NVIDIA."
    },
    "substituted_params": {
      "stock_code": null
    },
    "result": {
      "status": "error",
      "result": "A required parameter resolved to None, likely due to a failure in a dependency. Failed placeholder: '$outputs.get_company_profile_valid.ticker'"
    }
  },
  {
    "step": {
      "step_id": "get_splits_history_valid",
      "tool_name": "get_splits_history",
      "parameters": {
        "stock_code": "$outputs.get_company_profile_valid.ticker"
      },
      "description": "Dependent call: Query stock split history for NVIDIA."
    },
    "substituted_params": {
      "stock_code": null
    },
    "result": {
      "status": "error",
      "result": "A required parameter resolved to None, likely due to a failure in a dependency. Failed placeholder: '$outputs.get_company_profile_valid.ticker'"
    }
  },
  {
    "step": {
      "step_id": "get_ownership_data_valid",
      "tool_name": "get_ownership_data",
      "parameters": {
        "stock_code": "$outputs.get_company_profile_valid.ticker"
      },
      "description": "Dependent call: Retrieve ownership structure data for NVIDIA."
    },
    "substituted_params": {
      "stock_code": null
    },
    "result": {
      "status": "error",
      "result": "A required parameter resolved to None, likely due to a failure in a dependency. Failed placeholder: '$outputs.get_company_profile_valid.ticker'"
    }
  },
  {
    "step": {
      "step_id": "get_stock_prices_valid",
      "tool_name": "get_stock_prices",
      "parameters": {
        "stock_code": "$outputs.get_company_profile_valid.ticker",
        "start_date": "2023-01-01",
        "end_date": "2023-12-31"
      },
      "description": "Dependent call: Get historical stock price data for NVIDIA within a specific date range."
    },
    "substituted_params": {
      "stock_code": null,
      "start_date": "2023-01-01",
      "end_date": "2023-12-31"
    },
    "result": {
      "status": "error",
      "result": "A required parameter resolved to None, likely due to a failure in a dependency. Failed placeholder: '$outputs.get_company_profile_valid.ticker'"
    }
  },
  {
    "step": {
      "step_id": "get_market_news_valid",
      "tool_name": "get_market_news",
      "parameters": {
        "company_name": "NVIDIA"
      },
      "description": "Happy path: Fetch the latest market news related to NVIDIA."
    },
    "substituted_params": {
      "company_name": "NVIDIA"
    },
    "result": {
      "status": "error",
      "result": "Error executing tool get_market_news: HTTP error occurred: 404 - \n<!doctype html>\n<html lang=\"en\">\n<head>\n  <title>Not Found</title>\n</head>\n<body>\n  <h1>Not Found</h1><p>The requested resource was not found on this server.</p>\n</body>\n</html>\n"
    }
  },
  {
    "step": {
      "step_id": "get_company_profile_invalid_stock",
      "tool_name": "get_company_profile",
      "parameters": {
        "stock_code": "INVALID_STOCK"
      },
      "description": "Edge case: Test server behavior when an invalid stock code is provided."
    },
    "substituted_params": {
      "stock_code": "INVALID_STOCK"
    },
    "result": {
      "status": "error",
      "result": "Error executing tool get_company_profile: HTTP error occurred: 404 - \n<!doctype html>\n<html lang=\"en\">\n<head>\n  <title>Not Found</title>\n</head>\n<body>\n  <h1>Not Found</h1><p>The requested resource was not found on this server.</p>\n</body>\n</html>\n"
    }
  },
  {
    "step": {
      "step_id": "get_income_statements_invalid_limit",
      "tool_name": "get_income_statements",
      "parameters": {
        "stock_code": "NVDA",
        "report_period": "annual",
        "limit": -1
      },
      "description": "Edge case: Test server behavior when a negative limit is provided."
    },
    "substituted_params": {
      "stock_code": "NVDA",
      "report_period": "annual",
      "limit": -1
    },
    "result": {
      "status": "error",
      "result": "Error executing tool get_income_statements: HTTP error occurred: 301 - "
    }
  },
  {
    "step": {
      "step_id": "get_balance_sheets_invalid_period",
      "tool_name": "get_balance_sheets",
      "parameters": {
        "stock_code": "NVDA",
        "report_period": "invalid-period",
        "limit": 5
      },
      "description": "Edge case: Test server behavior when an unsupported report period is used."
    },
    "substituted_params": {
      "stock_code": "NVDA",
      "report_period": "invalid-period",
      "limit": 5
    },
    "result": {
      "status": "error",
      "result": "Error executing tool get_balance_sheets: HTTP error occurred: 301 - "
    }
  },
  {
    "step": {
      "step_id": "get_stock_prices_invalid_dates",
      "tool_name": "get_stock_prices",
      "parameters": {
        "stock_code": "NVDA",
        "start_date": "2025-01-01",
        "end_date": "2024-01-01"
      },
      "description": "Edge case: Test server behavior when start_date is after end_date."
    },
    "substituted_params": {
      "stock_code": "NVDA",
      "start_date": "2025-01-01",
      "end_date": "2024-01-01"
    },
    "result": {
      "status": "error",
      "result": "Error executing tool get_stock_prices: HTTP error occurred: 404 - \n<!doctype html>\n<html lang=\"en\">\n<head>\n  <title>Not Found</title>\n</head>\n<body>\n  <h1>Not Found</h1><p>The requested resource was not found on this server.</p>\n</body>\n</html>\n"
    }
  },
  {
    "step": {
      "step_id": "get_market_news_empty_company",
      "tool_name": "get_market_news",
      "parameters": {
        "company_name": ""
      },
      "description": "Edge case: Test server behavior when an empty company name is provided."
    },
    "substituted_params": {
      "company_name": ""
    },
    "result": {
      "status": "error",
      "result": "Error executing tool get_market_news: HTTP error occurred: 404 - \n<!doctype html>\n<html lang=\"en\">\n<head>\n  <title>Not Found</title>\n</head>\n<body>\n  <h1>Not Found</h1><p>The requested resource was not found on this server.</p>\n</body>\n</html>\n"
    }
  }
]