[
  {
    "step": {
      "step_id": "web_search_happy_path",
      "tool_name": "tavily_web_search",
      "parameters": {
        "query": "AI in healthcare",
        "search_depth": "basic",
        "max_results": 3
      },
      "description": "Happy path: Perform a basic web search for AI in healthcare with default parameters."
    },
    "substituted_params": {
      "query": "AI in healthcare",
      "search_depth": "basic",
      "max_results": 3
    },
    "result": {
      "status": "error",
      "result": "Error executing tool tavily_web_search: An unexpected error occurred while performing the web search: 'content_summary'"
    }
  },
  {
    "step": {
      "step_id": "validate_first_result_url",
      "tool_name": "tavily_web_search",
      "parameters": {
        "query": "$outputs.web_search_happy_path[0].url",
        "search_depth": "advanced"
      },
      "description": "Dependent call (key access): Use the URL from the first result of previous search as query for advanced search."
    },
    "substituted_params": {
      "query": null,
      "search_depth": "advanced"
    },
    "result": {
      "status": "error",
      "result": "A required parameter resolved to None, likely due to a failure in a dependency. Failed placeholder: '$outputs.web_search_happy_path[0].url'"
    }
  },
  {
    "step": {
      "step_id": "web_search_with_include_domains",
      "tool_name": "tavily_web_search",
      "parameters": {
        "query": "climate change research",
        "include_domains": [
          "example.com",
          "research.org"
        ],
        "max_results": 2
      },
      "description": "Test include domains filtering by specifying allowed domains in the search."
    },
    "substituted_params": {
      "query": "climate change research",
      "include_domains": [
        "example.com",
        "research.org"
      ],
      "max_results": 2
    },
    "result": {
      "status": "error",
      "result": "Error executing tool tavily_web_search: An unexpected error occurred while performing the web search: 'content_summary'"
    }
  },
  {
    "step": {
      "step_id": "web_search_with_exclude_domains",
      "tool_name": "tavily_web_search",
      "parameters": {
        "query": "quantum computing",
        "exclude_domains": [
          "wikipedia.org",
          "example.net"
        ],
        "max_results": 4
      },
      "description": "Test exclude domains filtering by excluding specific domains from the search results."
    },
    "substituted_params": {
      "query": "quantum computing",
      "exclude_domains": [
        "wikipedia.org",
        "example.net"
      ],
      "max_results": 4
    },
    "result": {
      "status": "error",
      "result": "Error executing tool tavily_web_search: An unexpected error occurred while performing the web search: 'content_summary'"
    }
  },
  {
    "step": {
      "step_id": "answer_search_happy_path",
      "tool_name": "tavily_answer_search",
      "parameters": {
        "query": "What are the benefits of renewable energy?",
        "max_results": 2
      },
      "description": "Happy path: Generate an answer to a factual question using supporting evidence."
    },
    "substituted_params": {
      "query": "What are the benefits of renewable energy?",
      "max_results": 2
    },
    "result": {
      "status": "error",
      "result": "Error executing tool tavily_answer_search: HTTP error occurred: 404 - {\"detail\":\"Not Found\"}"
    }
  },
  {
    "step": {
      "step_id": "use_answer_in_next_search",
      "tool_name": "tavily_web_search",
      "parameters": {
        "query": "$outputs.answer_search_happy_path",
        "search_depth": "advanced"
      },
      "description": "Dependent call (raw string): Use the generated answer as the query for an advanced web search."
    },
    "substituted_params": {
      "query": "Error executing tool tavily_answer_search: HTTP error occurred: 404 - {\"detail\":\"Not Found\"}",
      "search_depth": "advanced"
    },
    "result": {
      "status": "error",
      "result": "Error executing tool tavily_web_search: An unexpected error occurred while performing the web search: 'content_summary'"
    }
  },
  {
    "step": {
      "step_id": "news_search_happy_path",
      "tool_name": "tavily_news_search",
      "parameters": {
        "query": "latest advancements in AI",
        "days_back": 14,
        "max_results": 5
      },
      "description": "Happy path: Search recent news articles about AI within the last 14 days."
    },
    "substituted_params": {
      "query": "latest advancements in AI",
      "days_back": 14,
      "max_results": 5
    },
    "result": {
      "status": "error",
      "result": "Error executing tool tavily_news_search: HTTP error occurred: 404 - {\"detail\":\"Not Found\"}"
    }
  },
  {
    "step": {
      "step_id": "news_search_with_include_sources",
      "tool_name": "tavily_news_search",
      "parameters": {
        "query": "global economic trends",
        "include_sources": [
          "nytimes.com",
          "theguardian.com"
        ],
        "days_back": 7
      },
      "description": "Test include sources by restricting results to specified news outlets."
    },
    "substituted_params": {
      "query": "global economic trends",
      "include_sources": [
        "nytimes.com",
        "theguardian.com"
      ],
      "days_back": 7
    },
    "result": {
      "status": "error",
      "result": "Error executing tool tavily_news_search: HTTP error occurred: 404 - {\"detail\":\"Not Found\"}"
    }
  },
  {
    "step": {
      "step_id": "news_search_with_exclude_sources",
      "tool_name": "tavily_news_search",
      "parameters": {
        "query": "technology innovations",
        "exclude_sources": [
          "techcrunch.com",
          "theverge.com"
        ],
        "days_back": 30
      },
      "description": "Test exclude sources by filtering out results from specific tech news websites."
    },
    "substituted_params": {
      "query": "technology innovations",
      "exclude_sources": [
        "techcrunch.com",
        "theverge.com"
      ],
      "days_back": 30
    },
    "result": {
      "status": "error",
      "result": "Error executing tool tavily_news_search: HTTP error occurred: 404 - {\"detail\":\"Not Found\"}"
    }
  },
  {
    "step": {
      "step_id": "test_invalid_query_empty",
      "tool_name": "tavily_web_search",
      "parameters": {
        "query": "",
        "search_depth": "basic"
      },
      "description": "Edge case: Test server's handling of empty query input."
    },
    "substituted_params": {
      "query": "",
      "search_depth": "basic"
    },
    "result": {
      "status": "error",
      "result": "Error executing tool tavily_web_search: An unexpected error occurred while performing the web search: 'query' must be a non-empty string."
    }
  },
  {
    "step": {
      "step_id": "test_invalid_max_results",
      "tool_name": "tavily_answer_search",
      "parameters": {
        "query": "What is blockchain technology?",
        "max_results": -1
      },
      "description": "Edge case: Test server's handling of invalid max_results value."
    },
    "substituted_params": {
      "query": "What is blockchain technology?",
      "max_results": -1
    },
    "result": {
      "status": "error",
      "result": "Error executing tool tavily_answer_search: An unexpected error occurred while generating the answer: 'max_results' must be a positive integer."
    }
  },
  {
    "step": {
      "step_id": "test_invalid_days_back",
      "tool_name": "tavily_news_search",
      "parameters": {
        "query": "space exploration",
        "days_back": 500
      },
      "description": "Edge case: Test server's handling of out-of-range days_back parameter."
    },
    "substituted_params": {
      "query": "space exploration",
      "days_back": 500
    },
    "result": {
      "status": "error",
      "result": "Error executing tool tavily_news_search: An unexpected error occurred while searching for news articles: 'days_back' must be between 1 and 365."
    }
  },
  {
    "step": {
      "step_id": "test_unsupported_search_depth",
      "tool_name": "tavily_web_search",
      "parameters": {
        "query": "machine learning algorithms",
        "search_depth": "invalid_depth"
      },
      "description": "Edge case: Test server's handling of unsupported search depth."
    },
    "substituted_params": {
      "query": "machine learning algorithms",
      "search_depth": "invalid_depth"
    },
    "result": {
      "status": "error",
      "result": "Error executing tool tavily_web_search: An unexpected error occurred while performing the web search: 'search_depth' must be either 'basic' or 'advanced'."
    }
  }
]