{
  "final_decision_for_this_cycle": "DELIVERABLE",
  "reasoning": "Core functionality tests passed successfully, including listing tables, reading table contents, and executing SQL commands; failures were limited to edge cases and dependency resolution issues.",
  "refinement_loop_count": 1,
  "original_assessment": {
    "decision": "DELIVERABLE",
    "reason": "Core functionality tests passed successfully, including listing tables, reading table contents, and executing SQL commands; failures were limited to edge cases and dependency resolution issues."
  }
}